[    {
    "cartId": 1,
    "ingredientId":1,
    "name": "계란",
    "imageUrl": "https://image.zdnet.co.kr/2019/01/15/sini_1zwN8DfI5uThk94.jpg",
    "pinned": false
  },
  {
    "cartId": 2,
    "ingredientId":1,
    "name": "계란",
    "imageUrl": "https://image.zdnet.co.kr/2019/01/15/sini_1zwN8DfI5uThk94.jpg",
    "pinned": false
  },  {
    "cartId": 3,
    "ingredientId":1,
    "name": "계란",
    "imageUrl": "https://image.zdnet.co.kr/2019/01/15/sini_1zwN8DfI5uThk94.jpg",
    "pinned": false
  }
]